azure_status/__init__.py
azure_status-0.0.2.dist-info/LICENSE
azure_status-0.0.2.dist-info/METADATA
azure_status-0.0.2.dist-info/WHEEL
azure_status-0.0.2.dist-info/top_level.txt
azure_status-0.0.2.dist-info/RECORD
