Metadata-Version: 2.1
Name: azure-status
Version: 0.0.2
Summary: Azure Status Health page scraper
Home-page: https://github.com/fsniper/azure_status
Author: Onur Yalazi
Author-email: onur.yalazi@gmail.com
License: UNKNOWN
Platform: UNKNOWN
Classifier: Programming Language :: Python :: 3
Classifier: License :: OSI Approved :: MIT License
Classifier: Operating System :: OS Independent
Requires-Dist: requests
Requires-Dist: beautifulsoup4
